{
    "os": "Linux-6.6.6-76060606-generic-x86_64-with-glibc2.38",
    "python": "3.11.7",
    "heartbeatAt": "2024-01-04T18:43:32.217088",
    "startedAt": "2024-01-04T18:43:31.554682",
    "docker": null,
    "cuda": null,
    "args": [],
    "state": "running",
    "program": "/home/marjan/Documents/code-base/Aniso_MLMD/aniso_MLMD/trainer/sample_run_script.py",
    "codePathLocal": "sample_run_script.py",
    "codePath": "aniso_MLMD/trainer/sample_run_script.py",
    "git": {
        "remote": "git@github.com:marjanAlbouye/Aniso_MLMD.git",
        "commit": "fe81be598ae1068d8d9101f39fd483d7b78ee5ab"
    },
    "email": "marjan.albouye73@gmail.com",
    "root": "/home/marjan/Documents/code-base/Aniso_MLMD",
    "host": "pop-os",
    "username": "marjan",
    "executable": "/home/marjan/anaconda3/envs/anisoML/bin/python",
    "cpu_count": 8,
    "cpu_count_logical": 16,
    "cpu_freq": {
        "current": 800.2483750000001,
        "min": 800.0,
        "max": 4800.0
    },
    "cpu_freq_per_core": [
        {
            "current": 884.979,
            "min": 800.0,
            "max": 4800.0
        },
        {
            "current": 3251.025,
            "min": 800.0,
            "max": 4800.0
        },
        {
            "current": 885.766,
            "min": 800.0,
            "max": 4800.0
        },
        {
            "current": 800.0,
            "min": 800.0,
            "max": 4800.0
        },
        {
            "current": 800.024,
            "min": 800.0,
            "max": 4800.0
        },
        {
            "current": 943.563,
            "min": 800.0,
            "max": 4800.0
        },
        {
            "current": 800.069,
            "min": 800.0,
            "max": 4800.0
        },
        {
            "current": 1932.056,
            "min": 800.0,
            "max": 4800.0
        },
        {
            "current": 1540.572,
            "min": 800.0,
            "max": 4800.0
        },
        {
            "current": 803.913,
            "min": 800.0,
            "max": 4800.0
        },
        {
            "current": 799.979,
            "min": 800.0,
            "max": 4800.0
        },
        {
            "current": 1647.502,
            "min": 800.0,
            "max": 4800.0
        },
        {
            "current": 3168.013,
            "min": 800.0,
            "max": 4800.0
        },
        {
            "current": 1470.458,
            "min": 800.0,
            "max": 4800.0
        },
        {
            "current": 800.02,
            "min": 800.0,
            "max": 4800.0
        },
        {
            "current": 2287.516,
            "min": 800.0,
            "max": 4800.0
        }
    ],
    "disk": {
        "/": {
            "total": 15.622016906738281,
            "used": 0.0001220703125
        }
    },
    "gpu": "NVIDIA GeForce GTX TITAN X",
    "gpu_count": 1,
    "gpu_devices": [
        {
            "name": "NVIDIA GeForce GTX TITAN X",
            "memory_total": 12884901888
        }
    ],
    "memory": {
        "total": 31.244033813476562
    }
}
